email_validator/__init__.py
email_validator/__main__.py
email_validator/deliverability.py
email_validator/exceptions_types.py
email_validator/py.typed
email_validator/rfc_constants.py
email_validator/syntax.py
email_validator/validate_email.py
email_validator/version.py
email_validator-2.1.2.dist-info/LICENSE
email_validator-2.1.2.dist-info/METADATA
email_validator-2.1.2.dist-info/WHEEL
email_validator-2.1.2.dist-info/entry_points.txt
email_validator-2.1.2.dist-info/top_level.txt
email_validator-2.1.2.dist-info/RECORD
