Metadata-Version: 2.1
Name: email_validator
Version: 2.1.2
Summary: A robust email address syntax and deliverability validation library.
Home-page: https://github.com/JoshData/python-email-validator
Author: Joshua Tauberer
Author-email: jt@occams.info
License: Unlicense
Keywords: email address validator
Classifier: Development Status :: 5 - Production/Stable
Classifier: Intended Audience :: Developers
Classifier: License :: OSI Approved :: The Unlicense (Unlicense)
Classifier: Programming Language :: Python :: 3
Classifier: Programming Language :: Python :: 3.8
Classifier: Programming Language :: Python :: 3.9
Classifier: Programming Language :: Python :: 3.10
Classifier: Programming Language :: Python :: 3.11
Classifier: Programming Language :: Python :: 3.12
Classifier: Topic :: Software Development :: Libraries :: Python Modules
Requires-Python: >=3.8
License-File: LICENSE
Requires-Dist: dnspython>=2.0.0
Requires-Dist: idna>=2.0.0
